specphp_scanner/__init__.py
specphp_scanner/__main__.py
specphp_scanner/cli.py
specphp_scanner/auth/__init__.py
specphp_scanner/auth/base.py
specphp_scanner/auth/factory.py
specphp_scanner/core/__init__.py
specphp_scanner/core/result.py
specphp_scanner/core/scanner.py
specphp_scanner/utils/__init__.py
specphp_scanner/utils/param_generator.py
specphp_scanner/utils/report.py
specphp_scanner/utils/request_logger.py
specphp_scanner/utils/templates/report.html
specphp_scanner-0.0.13.dist-info/METADATA
specphp_scanner-0.0.13.dist-info/WHEEL
specphp_scanner-0.0.13.dist-info/entry_points.txt
specphp_scanner-0.0.13.dist-info/RECORD
