Metadata-Version: 2.4
Name: specphp-scanner
Version: 0.0.13
Summary: Add your description here
Requires-Python: >=3.12
Requires-Dist: click>=8.2.1
Requires-Dist: jinja2>=3.1.6
Requires-Dist: jsonschema>=4.21.0
Requires-Dist: pyyaml>=6.0.2
Requires-Dist: requests>=2.32.4
Requires-Dist: rich>=14.0.0
Requires-Dist: structlog>=25.4.0
Requires-Dist: typer>=0.16.0
